extra_requirements/requirements-docs.txt
extra_requirements/requirements-tests.txt
pema/__init__.py
pema/compare_plots.py
pema/contexts.py
pema/match_plugins.py
pema/matching.py
pema/misc.py
pema/scripts.py
pema/summary_plots.py
pema/wfsim_utils.py
pema-0.7.0.data/scripts/pema_init.py
pema-0.7.0.data/scripts/pema_straxer
tests/__init__.py
tests/test_basics.py
tests/test_matching.py
tests/test_stack.py
tests/test_wfsim_utils.py
pema-0.7.0.dist-info/METADATA
pema-0.7.0.dist-info/WHEEL
pema-0.7.0.dist-info/top_level.txt
pema-0.7.0.dist-info/RECORD
