Metadata-Version: 2.1
Name: pema
Version: 0.7.0
Summary: Peak matching for XENON simulations
Home-page: https://github.com/XENONnT/peakmatching
Author: Joran Angevaare
License: UNKNOWN
Platform: UNKNOWN
Classifier: Development Status :: 5 - Production/Stable
Classifier: License :: OSI Approved :: BSD License
Classifier: Natural Language :: English
Classifier: Programming Language :: Python :: 3.9
Classifier: Programming Language :: Python :: 3.10
Classifier: Intended Audience :: Science/Research
Classifier: Programming Language :: Python :: Implementation :: CPython
Classifier: Topic :: Scientific/Engineering :: Physics
Requires-Python: >=3.9
Requires-Dist: strax
Requires-Dist: utilix >=0.4.1
Requires-Dist: straxen >=2.2.0
Requires-Dist: wfsim >=1.2.0
Requires-Dist: multihist
Requires-Dist: numba
Requires-Dist: numpy
Requires-Dist: nestpy
Provides-Extra: docs
Requires-Dist: commonmark ==0.9.1 ; extra == 'docs'
Requires-Dist: graphviz ==0.20.1 ; extra == 'docs'
Requires-Dist: m2r ==0.2.1 ; extra == 'docs'
Requires-Dist: mistune ==0.8.4 ; extra == 'docs'
Requires-Dist: nbsphinx ==0.8.9 ; extra == 'docs'
Requires-Dist: recommonmark ==0.7.1 ; extra == 'docs'
Requires-Dist: sphinx ==7.1.2 ; extra == 'docs'
Requires-Dist: sphinx-rtd-theme ==1.3.0 ; extra == 'docs'
Requires-Dist: Jinja2 ==3.0.3 ; extra == 'docs'
Requires-Dist: urllib3 ==2.1.0 ; extra == 'docs'
